gradle.properties
hexdoc_hexkeys/__gradle_version__.py
hexdoc_hexkeys/__init__.py
hexdoc_hexkeys/__version__.py
hexdoc_hexkeys/_hooks.py
hexdoc_hexkeys/py.typed
hexdoc_hexkeys/_export/.gitignore
hexdoc_hexkeys/_export/__init__.py
hexdoc_hexkeys/_export/generated/__init__.py
hexdoc_hexkeys/_export/generated/hexkeys.hexdoc.json
hexdoc_hexkeys/_export/generated/hexkeys.patterns.hexdoc.json
hexdoc_hexkeys/_export/generated/assets/hexcasting/lang/en_us.flatten.json5
hexdoc_hexkeys/_export/generated/assets/hexkeys/lang/en_us.json
hexdoc_hexkeys/_export/generated/assets/hexkeys/lang/zh_cn.json
hexdoc_hexkeys/_export/generated/assets/hexkeys/models/block/mindscape_barrier.json
hexdoc_hexkeys/_export/generated/assets/hexkeys/models/item/mindscape_barrier.json
hexdoc_hexkeys/_export/generated/assets/hexkeys/textures/block/mindscape_barrier.png
hexdoc_hexkeys/_export/generated/data/hexdoc/tags/advancements/spoilered.json
hexdoc_hexkeys/_export/generated/data/hexkeys/patchouli_books/hexkeysbook/book.json
hexdoc_hexkeys/_export/generated/data/hexkeys/patchouli_books/hexkeysbook/en_us/entries/patterns/spells/kliens_chest.json
hexdoc_hexkeys/_export/generated/data/hexkeys/patchouli_books/hexkeysbook/en_us/entries/patterns/spells/mindscape.json
hexdoc_hexkeys/_export/generated/data/hexkeys/patchouli_books/hexkeysbook/en_us/entries/patterns/spells/visit_mindscape.json
hexdoc_hexkeys/_templates/__init__.py
hexdoc_hexkeys-0.1.3.1.0.dev0.dist-info/METADATA
hexdoc_hexkeys-0.1.3.1.0.dev0.dist-info/WHEEL
hexdoc_hexkeys-0.1.3.1.0.dev0.dist-info/entry_points.txt
hexdoc_hexkeys-0.1.3.1.0.dev0.dist-info/licenses/LICENSE.txt
hexdoc_hexkeys-0.1.3.1.0.dev0.dist-info/RECORD
