Metadata-Version: 2.3
Name: hexdoc-hexkeys
Version: 0.1.3.1.0.dev0
Summary: Python web book docgen and hexdoc plugin for Hex Keys.
Project-URL: Homepage, https://moonlitjolteon.github.io/hex-keys-addon
Project-URL: Source, https://github.com/MoonlitJolteon/hex-keys-addon
Author: MoonlitJolteon
License-File: LICENSE.txt
Keywords: hexdoc
Requires-Python: >=3.11
Requires-Dist: hexdoc-hexcasting~=0.10.3.1.0.dev22
Provides-Extra: dev
Requires-Dist: ruff~=0.1.4; extra == 'dev'
